{"nodes": [{"id": "users_e1621_documents_personal_android_heerr_android_app_lib_screens_job_detail_screen_dart", "label": "job_detail_screen.dart", "file_type": "code", "source_file": "android/app/lib/screens/job_detail_screen.dart", "source_location": null}, {"id": "screens_job_detail_screen_jobdetailscreen", "label": "JobDetailScreen", "file_type": "code", "source_file": "android/app/lib/screens/job_detail_screen.dart", "source_location": null}, {"id": "consumerwidget", "label": "ConsumerWidget", "file_type": "code", "source_file": null, "source_location": null}, {"id": "jobstatusprovider", "label": "jobStatusProvider", "file_type": "code", "source_file": null, "source_location": null}, {"id": "screens_job_detail_screen_jobbody", "label": "_JobBody", "file_type": "code", "source_file": "android/app/lib/screens/job_detail_screen.dart", "source_location": null}, {"id": "statelesswidget", "label": "StatelessWidget", "file_type": "code", "source_file": null, "source_location": null}, {"id": "screens_job_detail_screen_field", "label": "_Field", "file_type": "code", "source_file": "android/app/lib/screens/job_detail_screen.dart", "source_location": null}, {"id": "screens_job_detail_screen_timestampfield", "label": "_TimestampField", "file_type": "code", "source_file": "android/app/lib/screens/job_detail_screen.dart", "source_location": null}, {"id": "screens_job_detail_screen_errorfield", "label": "_ErrorField", "file_type": "code", "source_file": "android/app/lib/screens/job_detail_screen.dart", "source_location": null}, {"id": "screens_job_detail_screen_jobdetailskeleton", "label": "_JobDetailSkeleton", "file_type": "code", "source_file": "android/app/lib/screens/job_detail_screen.dart", "source_location": null}, {"id": "screens_job_detail_screen_jobid", "label": "jobId", "file_type": "code", "source_file": "android/app/lib/screens/job_detail_screen.dart", "source_location": null}, {"id": "screens_job_detail_screen_job", "label": "job", "file_type": "code", "source_file": "android/app/lib/screens/job_detail_screen.dart", "source_location": null}, {"id": "jobview", "label": "JobView", "file_type": "code", "source_file": null, "source_location": null}, {"id": "screens_job_detail_screen_label", "label": "label", "file_type": "code", "source_file": "android/app/lib/screens/job_detail_screen.dart", "source_location": null}, {"id": "screens_job_detail_screen_value", "label": "value", "file_type": "code", "source_file": "android/app/lib/screens/job_detail_screen.dart", "source_location": null}, {"id": "screens_job_detail_screen_copyable", "label": "copyable", "file_type": "code", "source_file": "android/app/lib/screens/job_detail_screen.dart", "source_location": null}, {"id": "screens_job_detail_screen_when", "label": "when", "file_type": "code", "source_file": "android/app/lib/screens/job_detail_screen.dart", "source_location": null}, {"id": "datetime", "label": "DateTime", "file_type": "code", "source_file": null, "source_location": null}, {"id": "screens_job_detail_screen_now", "label": "now", "file_type": "code", "source_file": "android/app/lib/screens/job_detail_screen.dart", "source_location": null}, {"id": "screens_job_detail_screen_message", "label": "message", "file_type": "code", "source_file": "android/app/lib/screens/job_detail_screen.dart", "source_location": null}, {"id": "screens_job_detail_screen_d", "label": "d", "file_type": "code", "source_file": "android/app/lib/screens/job_detail_screen.dart", "source_location": null}, {"id": "duration", "label": "Duration", "file_type": "code", "source_file": null, "source_location": null}, {"id": "screens_job_detail_screen_build", "label": "build", "file_type": "code", "source_file": "android/app/lib/screens/job_detail_screen.dart", "source_location": null}, {"id": "screens_job_detail_screen_copy", "label": "_copy", "file_type": "code", "source_file": "android/app/lib/screens/job_detail_screen.dart", "source_location": null}, {"id": "screens_job_detail_screen_short", "label": "_short", "file_type": "code", "source_file": "android/app/lib/screens/job_detail_screen.dart", "source_location": null}, {"id": "screens_job_detail_screen_relative", "label": "_relative", "file_type": "code", "source_file": "android/app/lib/screens/job_detail_screen.dart", "source_location": null}, {"id": "package_flutter_material_dart", "label": "package:flutter/material.dart", "file_type": "code", "source_file": null, "source_location": null}, {"id": "package_flutter_services_dart", "label": "package:flutter/services.dart", "file_type": "code", "source_file": null, "source_location": null}, {"id": "package_flutter_riverpod_flutter_riverpod_dart", "label": "package:flutter_riverpod/flutter_riverpod.dart", "file_type": "code", "source_file": null, "source_location": null}, {"id": "api_api_error_dart", "label": "../api/api_error.dart", "file_type": "code", "source_file": null, "source_location": null}, {"id": "models_job_view_dart", "label": "../models/job_view.dart", "file_type": "code", "source_file": null, "source_location": null}, {"id": "providers_job_status_dart", "label": "../providers/job_status.dart", "file_type": "code", "source_file": null, "source_location": null}, {"id": "widgets_error_snackbar_dart", "label": "../widgets/error_snackbar.dart", "file_type": "code", "source_file": null, "source_location": null}, {"id": "widgets_skeleton_dart", "label": "../widgets/skeleton.dart", "file_type": "code", "source_file": null, "source_location": null}, {"id": "widgets_status_pill_dart", "label": "../widgets/status_pill.dart", "file_type": "code", "source_file": null, "source_location": null}, {"id": "asyncvalue", "label": "AsyncValue", "file_type": "code", "source_file": null, "source_location": null}], "edges": [{"source": "users_e1621_documents_personal_android_heerr_android_app_lib_screens_job_detail_screen_dart", "target": "screens_job_detail_screen_jobdetailscreen", "relation": "defines", "confidence": "EXTRACTED", "confidence_score": 1.0, "source_file": "android/app/lib/screens/job_detail_screen.dart", "source_location": null, "weight": 1.0}, {"source": "screens_job_detail_screen_jobdetailscreen", "target": "consumerwidget", "relation": "inherits", "confidence": "EXTRACTED", "confidence_score": 1.0, "source_file": "android/app/lib/screens/job_detail_screen.dart", "source_location": null, "weight": 1.0}, {"source": "screens_job_detail_screen_jobdetailscreen", "target": "jobstatusprovider", "relation": "references", "confidence": "EXTRACTED", "confidence_score": 1.0, "source_file": "android/app/lib/screens/job_detail_screen.dart", "source_location": null, "weight": 1.0, "context": "riverpod_reference"}, {"source": "users_e1621_documents_personal_android_heerr_android_app_lib_screens_job_detail_screen_dart", "target": "screens_job_detail_screen_jobbody", "relation": "defines", "confidence": "EXTRACTED", "confidence_score": 1.0, "source_file": "android/app/lib/screens/job_detail_screen.dart", "source_location": null, "weight": 1.0}, {"source": "screens_job_detail_screen_jobbody", "target": "statelesswidget", "relation": "inherits", "confidence": "EXTRACTED", "confidence_score": 1.0, "source_file": "android/app/lib/screens/job_detail_screen.dart", "source_location": null, "weight": 1.0}, {"source": "users_e1621_documents_personal_android_heerr_android_app_lib_screens_job_detail_screen_dart", "target": "screens_job_detail_screen_field", "relation": "defines", "confidence": "EXTRACTED", "confidence_score": 1.0, "source_file": "android/app/lib/screens/job_detail_screen.dart", "source_location": null, "weight": 1.0}, {"source": "screens_job_detail_screen_field", "target": "statelesswidget", "relation": "inherits", "confidence": "EXTRACTED", "confidence_score": 1.0, "source_file": "android/app/lib/screens/job_detail_screen.dart", "source_location": null, "weight": 1.0}, {"source": "users_e1621_documents_personal_android_heerr_android_app_lib_screens_job_detail_screen_dart", "target": "screens_job_detail_screen_timestampfield", "relation": "defines", "confidence": "EXTRACTED", "confidence_score": 1.0, "source_file": "android/app/lib/screens/job_detail_screen.dart", "source_location": null, "weight": 1.0}, {"source": "screens_job_detail_screen_timestampfield", "target": "statelesswidget", "relation": "inherits", "confidence": "EXTRACTED", "confidence_score": 1.0, "source_file": "android/app/lib/screens/job_detail_screen.dart", "source_location": null, "weight": 1.0}, {"source": "users_e1621_documents_personal_android_heerr_android_app_lib_screens_job_detail_screen_dart", "target": "screens_job_detail_screen_errorfield", "relation": "defines", "confidence": "EXTRACTED", "confidence_score": 1.0, "source_file": "android/app/lib/screens/job_detail_screen.dart", "source_location": null, "weight": 1.0}, {"source": "screens_job_detail_screen_errorfield", "target": "statelesswidget", "relation": "inherits", "confidence": "EXTRACTED", "confidence_score": 1.0, "source_file": "android/app/lib/screens/job_detail_screen.dart", "source_location": null, "weight": 1.0}, {"source": "users_e1621_documents_personal_android_heerr_android_app_lib_screens_job_detail_screen_dart", "target": "screens_job_detail_screen_jobdetailskeleton", "relation": "defines", "confidence": "EXTRACTED", "confidence_score": 1.0, "source_file": "android/app/lib/screens/job_detail_screen.dart", "source_location": null, "weight": 1.0}, {"source": "screens_job_detail_screen_jobdetailskeleton", "target": "statelesswidget", "relation": "inherits", "confidence": "EXTRACTED", "confidence_score": 1.0, "source_file": "android/app/lib/screens/job_detail_screen.dart", "source_location": null, "weight": 1.0}, {"source": "users_e1621_documents_personal_android_heerr_android_app_lib_screens_job_detail_screen_dart", "target": "screens_job_detail_screen_jobid", "relation": "defines", "confidence": "EXTRACTED", "confidence_score": 1.0, "source_file": "android/app/lib/screens/job_detail_screen.dart", "source_location": null, "weight": 1.0}, {"source": "users_e1621_documents_personal_android_heerr_android_app_lib_screens_job_detail_screen_dart", "target": "screens_job_detail_screen_job", "relation": "defines", "confidence": "EXTRACTED", "confidence_score": 1.0, "source_file": "android/app/lib/screens/job_detail_screen.dart", "source_location": null, "weight": 1.0}, {"source": "users_e1621_documents_personal_android_heerr_android_app_lib_screens_job_detail_screen_dart", "target": "jobview", "relation": "references", "confidence": "EXTRACTED", "confidence_score": 1.0, "source_file": "android/app/lib/screens/job_detail_screen.dart", "source_location": null, "weight": 1.0, "context": "variable_type"}, {"source": "users_e1621_documents_personal_android_heerr_android_app_lib_screens_job_detail_screen_dart", "target": "screens_job_detail_screen_label", "relation": "defines", "confidence": "EXTRACTED", "confidence_score": 1.0, "source_file": "android/app/lib/screens/job_detail_screen.dart", "source_location": null, "weight": 1.0}, {"source": "users_e1621_documents_personal_android_heerr_android_app_lib_screens_job_detail_screen_dart", "target": "screens_job_detail_screen_value", "relation": "defines", "confidence": "EXTRACTED", "confidence_score": 1.0, "source_file": "android/app/lib/screens/job_detail_screen.dart", "source_location": null, "weight": 1.0}, {"source": "users_e1621_documents_personal_android_heerr_android_app_lib_screens_job_detail_screen_dart", "target": "screens_job_detail_screen_copyable", "relation": "defines", "confidence": "EXTRACTED", "confidence_score": 1.0, "source_file": "android/app/lib/screens/job_detail_screen.dart", "source_location": null, "weight": 1.0}, {"source": "users_e1621_documents_personal_android_heerr_android_app_lib_screens_job_detail_screen_dart", "target": "screens_job_detail_screen_label", "relation": "defines", "confidence": "EXTRACTED", "confidence_score": 1.0, "source_file": "android/app/lib/screens/job_detail_screen.dart", "source_location": null, "weight": 1.0}, {"source": "users_e1621_documents_personal_android_heerr_android_app_lib_screens_job_detail_screen_dart", "target": "screens_job_detail_screen_when", "relation": "defines", "confidence": "EXTRACTED", "confidence_score": 1.0, "source_file": "android/app/lib/screens/job_detail_screen.dart", "source_location": null, "weight": 1.0}, {"source": "users_e1621_documents_personal_android_heerr_android_app_lib_screens_job_detail_screen_dart", "target": "datetime", "relation": "references", "confidence": "EXTRACTED", "confidence_score": 1.0, "source_file": "android/app/lib/screens/job_detail_screen.dart", "source_location": null, "weight": 1.0, "context": "variable_type"}, {"source": "users_e1621_documents_personal_android_heerr_android_app_lib_screens_job_detail_screen_dart", "target": "screens_job_detail_screen_now", "relation": "defines", "confidence": "EXTRACTED", "confidence_score": 1.0, "source_file": "android/app/lib/screens/job_detail_screen.dart", "source_location": null, "weight": 1.0}, {"source": "users_e1621_documents_personal_android_heerr_android_app_lib_screens_job_detail_screen_dart", "target": "datetime", "relation": "references", "confidence": "EXTRACTED", "confidence_score": 1.0, "source_file": "android/app/lib/screens/job_detail_screen.dart", "source_location": null, "weight": 1.0, "context": "variable_type"}, {"source": "users_e1621_documents_personal_android_heerr_android_app_lib_screens_job_detail_screen_dart", "target": "screens_job_detail_screen_message", "relation": "defines", "confidence": "EXTRACTED", "confidence_score": 1.0, "source_file": "android/app/lib/screens/job_detail_screen.dart", "source_location": null, "weight": 1.0}, {"source": "users_e1621_documents_personal_android_heerr_android_app_lib_screens_job_detail_screen_dart", "target": "screens_job_detail_screen_d", "relation": "defines", "confidence": "EXTRACTED", "confidence_score": 1.0, "source_file": "android/app/lib/screens/job_detail_screen.dart", "source_location": null, "weight": 1.0}, {"source": "users_e1621_documents_personal_android_heerr_android_app_lib_screens_job_detail_screen_dart", "target": "duration", "relation": "references", "confidence": "EXTRACTED", "confidence_score": 1.0, "source_file": "android/app/lib/screens/job_detail_screen.dart", "source_location": null, "weight": 1.0, "context": "variable_type"}, {"source": "users_e1621_documents_personal_android_heerr_android_app_lib_screens_job_detail_screen_dart", "target": "screens_job_detail_screen_build", "relation": "defines", "confidence": "EXTRACTED", "confidence_score": 1.0, "source_file": "android/app/lib/screens/job_detail_screen.dart", "source_location": null, "weight": 1.0}, {"source": "screens_job_detail_screen_build", "target": "jobstatusprovider", "relation": "references", "confidence": "EXTRACTED", "confidence_score": 1.0, "source_file": "android/app/lib/screens/job_detail_screen.dart", "source_location": null, "weight": 1.0, "context": "riverpod_reference"}, {"source": "users_e1621_documents_personal_android_heerr_android_app_lib_screens_job_detail_screen_dart", "target": "screens_job_detail_screen_jobbody", "relation": "defines", "confidence": "EXTRACTED", "confidence_score": 1.0, "source_file": "android/app/lib/screens/job_detail_screen.dart", "source_location": null, "weight": 1.0}, {"source": "users_e1621_documents_personal_android_heerr_android_app_lib_screens_job_detail_screen_dart", "target": "screens_job_detail_screen_build", "relation": "defines", "confidence": "EXTRACTED", "confidence_score": 1.0, "source_file": "android/app/lib/screens/job_detail_screen.dart", "source_location": null, "weight": 1.0}, {"source": "users_e1621_documents_personal_android_heerr_android_app_lib_screens_job_detail_screen_dart", "target": "screens_job_detail_screen_field", "relation": "defines", "confidence": "EXTRACTED", "confidence_score": 1.0, "source_file": "android/app/lib/screens/job_detail_screen.dart", "source_location": null, "weight": 1.0}, {"source": "users_e1621_documents_personal_android_heerr_android_app_lib_screens_job_detail_screen_dart", "target": "screens_job_detail_screen_copy", "relation": "defines", "confidence": "EXTRACTED", "confidence_score": 1.0, "source_file": "android/app/lib/screens/job_detail_screen.dart", "source_location": null, "weight": 1.0}, {"source": "users_e1621_documents_personal_android_heerr_android_app_lib_screens_job_detail_screen_dart", "target": "screens_job_detail_screen_build", "relation": "defines", "confidence": "EXTRACTED", "confidence_score": 1.0, "source_file": "android/app/lib/screens/job_detail_screen.dart", "source_location": null, "weight": 1.0}, {"source": "users_e1621_documents_personal_android_heerr_android_app_lib_screens_job_detail_screen_dart", "target": "screens_job_detail_screen_timestampfield", "relation": "defines", "confidence": "EXTRACTED", "confidence_score": 1.0, "source_file": "android/app/lib/screens/job_detail_screen.dart", "source_location": null, "weight": 1.0}, {"source": "users_e1621_documents_personal_android_heerr_android_app_lib_screens_job_detail_screen_dart", "target": "screens_job_detail_screen_build", "relation": "defines", "confidence": "EXTRACTED", "confidence_score": 1.0, "source_file": "android/app/lib/screens/job_detail_screen.dart", "source_location": null, "weight": 1.0}, {"source": "users_e1621_documents_personal_android_heerr_android_app_lib_screens_job_detail_screen_dart", "target": "screens_job_detail_screen_errorfield", "relation": "defines", "confidence": "EXTRACTED", "confidence_score": 1.0, "source_file": "android/app/lib/screens/job_detail_screen.dart", "source_location": null, "weight": 1.0}, {"source": "users_e1621_documents_personal_android_heerr_android_app_lib_screens_job_detail_screen_dart", "target": "screens_job_detail_screen_build", "relation": "defines", "confidence": "EXTRACTED", "confidence_score": 1.0, "source_file": "android/app/lib/screens/job_detail_screen.dart", "source_location": null, "weight": 1.0}, {"source": "users_e1621_documents_personal_android_heerr_android_app_lib_screens_job_detail_screen_dart", "target": "screens_job_detail_screen_jobdetailskeleton", "relation": "defines", "confidence": "EXTRACTED", "confidence_score": 1.0, "source_file": "android/app/lib/screens/job_detail_screen.dart", "source_location": null, "weight": 1.0}, {"source": "users_e1621_documents_personal_android_heerr_android_app_lib_screens_job_detail_screen_dart", "target": "screens_job_detail_screen_build", "relation": "defines", "confidence": "EXTRACTED", "confidence_score": 1.0, "source_file": "android/app/lib/screens/job_detail_screen.dart", "source_location": null, "weight": 1.0}, {"source": "users_e1621_documents_personal_android_heerr_android_app_lib_screens_job_detail_screen_dart", "target": "screens_job_detail_screen_short", "relation": "defines", "confidence": "EXTRACTED", "confidence_score": 1.0, "source_file": "android/app/lib/screens/job_detail_screen.dart", "source_location": null, "weight": 1.0}, {"source": "users_e1621_documents_personal_android_heerr_android_app_lib_screens_job_detail_screen_dart", "target": "screens_job_detail_screen_relative", "relation": "defines", "confidence": "EXTRACTED", "confidence_score": 1.0, "source_file": "android/app/lib/screens/job_detail_screen.dart", "source_location": null, "weight": 1.0}, {"source": "users_e1621_documents_personal_android_heerr_android_app_lib_screens_job_detail_screen_dart", "target": "package_flutter_material_dart", "relation": "imports", "confidence": "EXTRACTED", "confidence_score": 1.0, "source_file": "android/app/lib/screens/job_detail_screen.dart", "source_location": null, "weight": 1.0}, {"source": "users_e1621_documents_personal_android_heerr_android_app_lib_screens_job_detail_screen_dart", "target": "package_flutter_services_dart", "relation": "imports", "confidence": "EXTRACTED", "confidence_score": 1.0, "source_file": "android/app/lib/screens/job_detail_screen.dart", "source_location": null, "weight": 1.0}, {"source": "users_e1621_documents_personal_android_heerr_android_app_lib_screens_job_detail_screen_dart", "target": "package_flutter_riverpod_flutter_riverpod_dart", "relation": "imports", "confidence": "EXTRACTED", "confidence_score": 1.0, "source_file": "android/app/lib/screens/job_detail_screen.dart", "source_location": null, "weight": 1.0}, {"source": "users_e1621_documents_personal_android_heerr_android_app_lib_screens_job_detail_screen_dart", "target": "api_api_error_dart", "relation": "imports", "confidence": "EXTRACTED", "confidence_score": 1.0, "source_file": "android/app/lib/screens/job_detail_screen.dart", "source_location": null, "weight": 1.0}, {"source": "users_e1621_documents_personal_android_heerr_android_app_lib_screens_job_detail_screen_dart", "target": "models_job_view_dart", "relation": "imports", "confidence": "EXTRACTED", "confidence_score": 1.0, "source_file": "android/app/lib/screens/job_detail_screen.dart", "source_location": null, "weight": 1.0}, {"source": "users_e1621_documents_personal_android_heerr_android_app_lib_screens_job_detail_screen_dart", "target": "providers_job_status_dart", "relation": "imports", "confidence": "EXTRACTED", "confidence_score": 1.0, "source_file": "android/app/lib/screens/job_detail_screen.dart", "source_location": null, "weight": 1.0}, {"source": "users_e1621_documents_personal_android_heerr_android_app_lib_screens_job_detail_screen_dart", "target": "widgets_error_snackbar_dart", "relation": "imports", "confidence": "EXTRACTED", "confidence_score": 1.0, "source_file": "android/app/lib/screens/job_detail_screen.dart", "source_location": null, "weight": 1.0}, {"source": "users_e1621_documents_personal_android_heerr_android_app_lib_screens_job_detail_screen_dart", "target": "widgets_skeleton_dart", "relation": "imports", "confidence": "EXTRACTED", "confidence_score": 1.0, "source_file": "android/app/lib/screens/job_detail_screen.dart", "source_location": null, "weight": 1.0}, {"source": "users_e1621_documents_personal_android_heerr_android_app_lib_screens_job_detail_screen_dart", "target": "widgets_status_pill_dart", "relation": "imports", "confidence": "EXTRACTED", "confidence_score": 1.0, "source_file": "android/app/lib/screens/job_detail_screen.dart", "source_location": null, "weight": 1.0}, {"source": "users_e1621_documents_personal_android_heerr_android_app_lib_screens_job_detail_screen_dart", "target": "asyncvalue", "relation": "references", "confidence": "EXTRACTED", "confidence_score": 1.0, "source_file": "android/app/lib/screens/job_detail_screen.dart", "source_location": null, "weight": 1.0, "context": "type_lookup"}, {"source": "users_e1621_documents_personal_android_heerr_android_app_lib_screens_job_detail_screen_dart", "target": "jobview", "relation": "references", "confidence": "EXTRACTED", "confidence_score": 1.0, "source_file": "android/app/lib/screens/job_detail_screen.dart", "source_location": null, "weight": 1.0, "context": "type_lookup"}]}